dashai_phi_model_package/__init__.py
dashai_phi_model_package/phi_model.py
dashai_phi_model_package-0.0.2.dist-info/METADATA
dashai_phi_model_package-0.0.2.dist-info/WHEEL
dashai_phi_model_package-0.0.2.dist-info/entry_points.txt
dashai_phi_model_package-0.0.2.dist-info/RECORD
